infra_analytics/__init__.py
infra_analytics/config.py
infra_analytics/crawlerAreaWard.py
infra_analytics/crawlerShopFtel.py
infra_analytics/crawlerShopdienmay.py
infra_analytics/data_import.py
infra_analytics/feature_ptht.py
infra_analytics/hieuquakhaithac.py
infra_analytics/infor_port_monthly.py
infra_analytics/insert_dashboard_bi.py
infra_analytics/model_training.py
infra_analytics/splitter_level2.py
infra_analytics/tangtruongport.py
infra_analytics-0.1.3.dist-info/METADATA
infra_analytics-0.1.3.dist-info/WHEEL
infra_analytics-0.1.3.dist-info/license
infra_analytics-0.1.3.dist-info/top_level.txt
infra_analytics-0.1.3.dist-info/RECORD
