Metadata-Version: 2.1
Name: infra-analytics
Version: 0.1.3
Summary: Sort description
Home-page: https://github.com/pypa/sampleproject
Author: hautx2
Author-email: hautx2@fpt.com
Classifier: Programming Language :: Python :: 3
Classifier: License :: OSI Approved :: MIT License
Classifier: Operating System :: OS Independent
License-File: license
